Workbook

Sheet ABC-XYZ
B1: name | C1: kol | D1: zak | E1: roz | F1: perc_kol | G1: cumsum_kol | H1: margin | I1: abc_kol | J1: perc_roz | K1: cumsum_roz | L1: abc_roz | M1: margin | N1: perc_marg | O1: cumsum_marg | P1: abc_margin | Q1: ABC | R1: var | S1: XYZ | T1: ABC XYZ
B2: ЛЮКСПЛАСТ ЛЕЙКОПЛАСТ, БАКТЕР, 19Х72ММ ТКАН, ЭЛ,ТЕЛЕСН, №10 [LUXPLAST] | C2: 151 | D2: 5975.18 | E2: 9692 | F2: 0.0096670266 | G2: 0.42502907 | H2: 0.3834936 | I2: A | J2: 0.0048307583 | K2: 0.79458725 | L2: A | M2: 0.3834936 | N2: 0.0097256527 | O2: 0.19150033 | P2: A | Q2: AAA | R2: 0.84514713 | S2: =IF(R2<0.1,"X",IF(R2<0.25,"Y","Z")) -> Z | T2: =Q2&S2 -> AAAZ
B3: УГОЛЬ АКТИВИРОВАННЫЙ 250МГ, №50 ТАБ, /ФАРМСТАНДАРТ ЛЕКСРЕДСТВА/ | C3: 179 | D3: 7147.68 | E3: 11109 | F3: 0.011459588 | G3: 0.34103477 | H3: 0.35658655 | I3: A | J3: 0.0055370299 | K3: 0.76418103 | L3: A | M3: 0.35658655 | N3: 0.009043272 | O3: 0.31183028 | P3: A | Q3: AAA | R3: 0.63202543 | S3: =IF(R3<0.1,"X",IF(R3<0.25,"Y","Z")) -> Z | T3: =Q3&S3 -> AAAZ
B4: ЦИТРАМОН П №20 ТАБ, /ФАРМСТАНДАРТ/ | C4: 173 | D4: 7460.08 | E4: 11585 | F4: 0.011075468 | G4: 0.36350581 | H4: 0.35605697 | I4: A | J4: 0.0057742813 | K4: 0.75292853 | L4: A | M4: 0.35605697 | N4: 0.0090298414 | O4: 0.32086013 | P4: A | Q4: AAA | R4: 0.61817081 | S4: =IF(R4<0.1,"X",IF(R4<0.25,"Y","Z")) -> Z | T4: =Q4&S4 -> AAAZ
B5: ВАЛЕРИАНА ЭКСТРАКТ 20МГ, №50 ТАБ, П/О /БОРИСОВСКИЙ/ | C5: 154 | D5: 6918.05 | E5: 10742 | F5: 0.0098590867 | G5: 0.41536204 | H5: 0.3559812 | I5: A | J5: 0.005354107 | K5: 0.76953513 | L5: A | M5: 0.3559812 | N5: 0.0090279197 | O5: 0.32988804 | P5: A | Q5: AAA | R5: 0.61844536 | S5: =IF(R5<0.1,"X",IF(R5<0.25,"Y","Z")) -> Z | T5: =Q5&S5 -> AAAZ
B6: СФМ ШПРИЦ 2МЛ, 3-Х КОМП, 0,63Х32ММ 23G №10 [SFM] | C6: 78.1 | D6: 10120.01 | E6: 15669.55 | F6: 0.0049999654 | G6: 0.71809042 | H6: 0.35416078 | I6: A | J6: 0.0078101329 | K6: 0.67375554 | L6: A | M6: 0.35416078 | N6: 0.0089817527 | O6: 0.36588028 | P6: A | Q6: AAA | R6: 0.7195565 | S6: =IF(R6<0.1,"X",IF(R6<0.25,"Y","Z")) -> Z | T6: =Q6&S6 -> AAAZ
B7: СФМ ШПРИЦ 5МЛ, 3-Х КОМП, 0,7Х40ММ 22G №10 [SFM] | C7: 115.6 | D7: 17169.07 | E7: 26582 | F7: 0.007400717 | G7: 0.54869018 | H7: 0.35410917 | I7: A | J7: 0.013249197 | K7: 0.50313592 | L7: A | M7: 0.35410917 | N7: 0.008980444 | O7: 0.37486072 | P7: A | Q7: AAA | R7: 0.52749727 | S7: =IF(R7<0.1,"X",IF(R7<0.25,"Y","Z")) -> Z | T7: =Q7&S7 -> AAAZ
B8: КЕТОРОЛ ЭКСПРЕСС 10МГ, №20 ТАБ, ДИСПЕРГ, /Д-Р РЕДДИС/ | C8: 194 | D8: 8596.1 | E8: 13278 | F8: 0.012419888 | G8: 0.293852 | H8: 0.35260581 | I8: A | J8: 0.0066181189 | K8: 0.71609147 | L8: A | M8: 0.35260581 | N8: 0.0089423178 | O8: 0.39277044 | P8: A | Q8: AAA | R8: 0.6886848 | S8: =IF(R8<0.1,"X",IF(R8<0.25,"Y","Z")) -> Z | T8: =Q8&S8 -> AAAZ
B9: РОМАШКИ ЦВЕТКИ 1,5Г, №20 ПАК, /КРАСНОГОРСК/ | C9: 142 | D9: 10064.98 | E9: 14512 | F9: 0.0090908462 | G9: 0.44353086 | H9: 0.30643743 | I9: A | J9: 0.0072331783 | K9: 0.68860668 | L9: A | M9: 0.30643743 | N9: 0.0077714569 | O9: 0.49175547 | P9: A | Q9: AAA | R9: 0.61168835 | S9: =IF(R9<0.1,"X",IF(R9<0.25,"Y","Z")) -> Z | T9: =Q9&S9 -> AAAZ
B10: ЛЕВОМЕКОЛЬ 40МГ/Г,+7,5МГ/Г, 40Г, №1 МАЗЬ Д/НАРУЖ,ПРИМ, ТУБА /НИЖФАРМ/ | C10: 118 | D10: 17345.1 | E10: 24172 | F10: 0.0075543651 | G10: 0.52630878 | H10: 0.28243008 | I10: A | J10: 0.012047987 | K10: 0.52784446 | L10: A | M10: 0.28243008 | N10: 0.0071626147 | O10: 0.51425745 | P10: A | Q10: AAA | R10: 0.69066764 | S10: =IF(R10<0.1,"X",IF(R10<0.25,"Y","Z")) -> Z | T10: =Q10&S10 -> AAAZ
B11: ИНГАЛИПТ 30МЛ, АЭРОЗОЛЬ Д/МЕСТ,ПРИМ, БАЛЛОН /ФАРМСТАНДАРТ-ЛЕКСРЕДСТВА/ | C11: 72 | D11: 8670.44 | E11: 12055 | F11: 0.0046094431 | G11: 0.73702755 | H11: 0.28075985 | I11: A | J11: 0.0060085422 | K11: 0.74124756 | L11: A | M11: 0.28075985 | N11: 0.0071202564 | O11: 0.5213777 | P11: A | Q11: AAA | R11: 0.746417 | S11: =IF(R11<0.1,"X",IF(R11<0.25,"Y","Z")) -> Z | T11: =Q11&S11 -> AAAZ
B12: СПАЗМАЛГОН №20 ТАБ, | C12: 81 | D12: 14922.95 | E12: 20729 | F12: 0.0051856235 | G12: 0.70291127 | H12: 0.28009311 | I12: A | J12: 0.010331901 | K12: 0.59428864 | L12: A | M12: 0.28009311 | N12: 0.0071033473 | O12: 0.53558655 | P12: A | Q12: AAA | R12: 0.6937732 | S12: =IF(R12<0.1,"X",IF(R12<0.25,"Y","Z")) -> Z | T12: =Q12&S12 -> AAAZ
B13: ИБУКЛИН 400МГ,+325МГ, №10 ТАБ, П/П/О | C13: 69 | D13: 9379.31 | E13: 12954.92 | F13: 0.004417383 | G13: 0.76397999 | H13: 0.27600402 | I13: A | J13: 0.006457087 | K13: 0.72254855 | L13: A | M13: 0.27600402 | N13: 0.0069996454 | O13: 0.54965908 | P13: A | Q13: AAA | R13: 1.0418874 | S13: =IF(R13<0.1,"X",IF(R13<0.25,"Y","Z")) -> Z | T13: =Q13&S13 -> AAAZ
... B157: ТРИХОПОЛ 250МГ, №20 ТАБ, /ПОЛЬФАРМА/ | C157: 42 | D157: 3019.17 | E157: 3706 | F157: 0.0026888418 | G157: 0.97592474 | H157: 0.1853292 | I157: C | J157: 0.0018471719 | K157: 0.95839691 | L157: C | M157: 0.1853292 | N157: 0.0047000716 | O157: 0.79808945 | P157: B | Q157: CCB | R157: 1.1998411 | S157: =IF(R157<0.1,"X",IF(R157<0.25,"Y","Z")) -> Z | T157: =Q157&S157 -> CCBZ

Sheet Мой abc
A3: Названия строк | B3: Сумма по столбцу dr_kol | C3: Сумма по столбцу dr_czak | D3: Сумма по столбцу dr_croz | F3: pr_kol
A4: ЛЕЙКОПЛАСТЫРЬ БАКТЕР, 2,5Х7,2 №1 /ВЕРОФАРМ/ | B4: 862 | C4: 184.92 | D4: 341.34 | F4: =GETPIVOTDATA("[Measures].[Сумма по столбцу dr_kol]",$A$3,"[Диапазон].[dr_ndrugs]","[Диапазон].[dr_ndrugs].&[ЛЕЙКОПЛАСТЫРЬ БАКТЕР, 2,5Х7,2 №1 /ВЕРОФАРМ/]")/SUM(B:B) -> 0.027592639
A5: НАФТИЗИН 0,1% 15МЛ, НАЗАЛ,КАПЛИ ФЛ,/КАП, /СЛАВЯНСКАЯ АПТЕКА/ | B5: 582 | C5: 688.15 | D5: 956 | F5: =GETPIVOTDATA("[Measures].[Сумма по столбцу dr_kol]",$A$3,"[Диапазон].[dr_ndrugs]","[Диапазон].[dr_ndrugs].&[ЛЕЙКОПЛАСТЫРЬ БАКТЕР, 2,5Х7,2 №1 /ВЕРОФАРМ/]")/SUM(B:B) -> 0.027592639
A6: КОРВАЛОЛ 25МЛ, КАПЛИ Д/ПРИЕМА ВНУТРЬ ФЛ, И/У /ФАРМСТАНДАРТ ЛЕКСРЕДСТВА/ | B6: 351 | C6: 7230.24 | D6: 9242.35 | F6: =GETPIVOTDATA("[Measures].[Сумма по столбцу dr_kol]",$A$3,"[Диапазон].[dr_ndrugs]","[Диапазон].[dr_ndrugs].&[ЛЕЙКОПЛАСТЫРЬ БАКТЕР, 2,5Х7,2 №1 /ВЕРОФАРМ/]")/SUM(B:B) -> 0.027592639
A7: СНУП 0,1% 90МКГ/ДОЗА 15МЛ, НАЗАЛ,СПРЕЙ ФЛ, /ШТАДА/ | B7: 319 | C7: 31551.9 | D7: 37411.68 | F7: =GETPIVOTDATA("[Measures].[Сумма по столбцу dr_kol]",$A$3,"[Диапазон].[dr_ndrugs]","[Диапазон].[dr_ndrugs].&[ЛЕЙКОПЛАСТЫРЬ БАКТЕР, 2,5Х7,2 №1 /ВЕРОФАРМ/]")/SUM(B:B) -> 0.027592639
A8: НАФТИЗИН 0,1% 15МЛ, НАЗАЛ,КАПЛИ ФЛ,/КАП, /ЛЕККО/ | B8: 296 | C8: 3955.44 | D8: 5393 | F8: =GETPIVOTDATA("[Measures].[Сумма по столбцу dr_kol]",$A$3,"[Диапазон].[dr_ndrugs]","[Диапазон].[dr_ndrugs].&[ЛЕЙКОПЛАСТЫРЬ БАКТЕР, 2,5Х7,2 №1 /ВЕРОФАРМ/]")/SUM(B:B) -> 0.027592639
A9: ВАЛИДОЛ 60МГ, №10 ТАБ, ПОДЪЯЗЫЧ, /ФАРМСТАНДАРТ/ | B9: 276 | C9: 8445.27 | D9: 9877 | F9: =GETPIVOTDATA("[Measures].[Сумма по столбцу dr_kol]",$A$3,"[Диапазон].[dr_ndrugs]","[Диапазон].[dr_ndrugs].&[ЛЕЙКОПЛАСТЫРЬ БАКТЕР, 2,5Х7,2 №1 /ВЕРОФАРМ/]")/SUM(B:B) -> 0.027592639
A10: ФЕРРОГЕМАТОГЕН 50Г, ПАСТИЛКА ЖЕВ, (ПЛИТКА) | B10: 273 | C10: 4185.18 | D10: 6797
A11: БОРНАЯ К-ТА 10Г, ДЕЗ,СР-ВО ПОР, (НДС 20%) | B11: 271 | C11: 977.14 | D11: 1618
A12: ПЕНТАЛГИН №24 ТАБ, П/П/О /ОТИСИФАРМ/ | B12: 261 | C12: 47685.42 | D12: 56782
A13: ТИЗИН КЛАССИК 0,1% 10МЛ, НАЗАЛ,СПРЕЙ ФЛ, /ДЖОНСОН/ | B13: 236 | C13: 20956.41 | D13: 25401
A14: ЛЕЙКОПЛАСТЫРЬ БАКТЕР, 6X10 №1 /ВЕРОФАРМ/ | B14: 227 | C14: 254.28 | D14: 428
A15: ОМЕЗ 20МГ, №30 КАПС, /Д-Р РЕДДИ/ | B15: 225 | C15: 33284.62 | D15: 39989.77
A16: ПУСТЫРНИКА НАСТОЙКА 25МЛ, ФЛ, /ГИППОКРАТ/ | B16: 217 | C16: 5074.17 | D16: 6439
A17: КЕТОРОЛ ЭКСПРЕСС 10МГ, №20 ТАБ, ДИСПЕРГ, /Д-Р РЕДДИС/ | B17: 194 | C17: 8596.1 | D17: 13278
A18: ТАУФОН 4% 10МЛ, №1 ГЛ,КАПЛИ ФЛ,/КАП, /ОТИСИФАРМ/ФАРМСТАНДАРТ/ | B18: 191 | C18: 21445.24 | D18: 24020.64
A19: ЦЕФТРИАКСОН 1Г, №1 ПОР, Д/Р-РА Д/В/В,В/М ФЛ, /БИОСИНТЕЗ/ | B19: 187 | C19: 5156.48 | D19: 6567.36
A20: РИНОСТОП 0,1% 15МЛ, НАЗАЛ,СПРЕЙ ФЛ, /ОТИСИФАРМ/ЛЕККО/ФАРМСТАНДАРТ ЛЕКСРЕДСТВА/ | B20: 180 | C20: 14766 | D20: 18583
A21: УГОЛЬ АКТИВИРОВАННЫЙ 250МГ, №50 ТАБ, /ФАРМСТАНДАРТ ЛЕКСРЕДСТВА/ | B21: 179 | C21: 7147.68 | D21: 11109
... A160: Общий итог | B160: 15620.108 | C160: 1558844.8 | D160: 2006310.3

Sheet Сводник кол-во по каждой кат.
C1: количество, выручка, маржинальность
A3: Названия строк | B3: Количество по полю ABC
A4: AAA | B4: 13
A5: AAB | B5: 11
A6: AAC | B6: 10
A7: ABA | B7: 14
A8: ABB | B8: 16
A9: ACA | B9: 16
A10: ACB | B10: 6
A11: ACC | B11: 2
A12: BAA | B12: 3
A13: BAB | B13: 7
A14: BAC | B14: 6
A15: BBA | B15: 5
... A28: CCB | B28: 3
A29: (пусто)
A30: Общий итог | B30: 156

Sheet Сводник по каждому тов.
A3: Названия строк | B3: Сумма по полю dr_kol | C3: Сумма по полю dr_czak | D3: Сумма по полю dr_croz
A4: L-ТИРОКСИН 50МКГ, №50 ТАБ, /БЕРЛИН ХЕМИ/ | B4: 45 | C4: 3933.7 | D4: 4598
A5: АКВАДЕТРИМ 15000МЕ/МЛ, 10МЛ, КАПЛИ Д/ПРИЕМА ВНУТРЬ ФЛ,/КАП, (ВИТАМИН Д3 ВОДН,Р-Р) /МЕДАНА/ | B5: 43 | C5: 7053.69 | D5: 8342.02
A6: АЛЛОХОЛ №50 ТАБ, П/О /ФАРМСТАНДАРТ/ | B6: 49 | C6: 2350.61 | D6: 3578
A7: АММИАК 100МГ/МЛ, 100МЛ, №1 Р-Р Д/НАРУЖ,/ИНГ, ФЛ, /САМАРСКАЯ ФФ/ | B7: 165 | C7: 2645.2 | D7: 4177
A8: АНАЛЬГИН 500МГ, №20 ТАБ, /ФАРМСТАНДАРТ/ | B8: 115 | C8: 4234.6 | D8: 6551
A9: АСЕПТИКА САЛФЕТКА СПИРТОВАЯ 60Х100 №20 | B9: 97.95 | C9: 3180.74 | D9: 5289
A10: АСЕПТИКА САЛФЕТКА СПИРТОВАЯ 60Х100 №30 | B10: 88 | C10: 3272.91 | D10: 5311
A11: АСКОРБИНОВАЯ К-ТА 100МГ,+877МГ, ГЛЮКОЗА №40 ТАБ, /ФАРМСТАНДАРТ/ | B11: 45 | C11: 1449.02 | D11: 2273
A12: АСКОРБИНОВАЯ К-ТА 25МГ, №10 ТАБ, КРУТКА САХ, (БАД) | B12: 142 | C12: 1188 | D12: 1997
A13: АСКОРБИНОВАЯ К-ТА 50МГ, №200 ДРАЖЕ /ФАРМСТАНДАРТ-УФАВИТА/ | B13: 51 | C13: 997.38 | D13: 1209
A14: АСКОРБИНОВАЯ К-ТА АПЕЛЬСИН №10 ТАБ, КРУТКА САХ, | B14: 70 | C14: 431.67 | D14: 722
A15: АСКОРУТИН 50МГ,+50МГ, №50 ТАБ, /ФАРМСТАНДАРТ-УФИМСКИЙ/ | B15: 48 | C15: 2062.03 | D15: 3207
... A160: Общий итог | B160: 15620.108 | C160: 1558844.8 | D160: 2006310.3

Sheet data
A1: dr_ndrugs | B1: dr_dat | C1: dr_kol | D1: dr_czak | E1: dr_croz
A2: КОНКОР КОР 2,5МГ, №30 ТАБ, П/П/О /МЕРК/ | B2: 44721 | C2: 1 | D2: 130.15 | E2: 157 | H2: =MIN(B:B) -> 44682
A3: ТЕРАФЛЮ ЛИМОН ОТ ГРИППА И ПРОСТУДЫ 22,1Г, №10 ПОР, Д/Р-РА Д/ПРИЕМА ВНУТРЬ ПАК, | B3: 44721 | C3: 0.4 | D3: 458.65 | E3: 574 | H3: =MAX(B:B) -> 44721
A4: ТИЗИН КЛАССИК 0,1% 10МЛ, НАЗАЛ,СПРЕЙ ФЛ, /ДЖОНСОН/ | B4: 44721 | C4: 1 | D4: 88.43 | E4: 110
A5: ЛЮКСПЛАСТ ЛЕЙКОПЛАСТ, БАКТЕР, 19Х72ММ ТКАН, ЭЛ,ТЕЛЕСН, №10 [LUXPLAST] | B5: 44721 | C5: 1 | D5: 47.67 | E5: 77
A6: РИНОНОРМ-ТЕВА 0,1% 140МКГ/ДОЗА 20МЛ, НАЗАЛ,СПРЕЙ ФЛ, /ТЕВА/ | B6: 44721 | C6: 1 | D6: 80.69 | E6: 98
A7: ХЛОРГЕКСИДИН 0,05% 100МЛ, №1 Р-Р Д/МЕСТ, И НАРУЖ,ПРИМ, ФЛ, ПЭТ, /ТУЛЬСКАЯ ФФ/ | B7: 44721 | C7: 1 | D7: 11.1 | E7: 13
A8: СТЭЛМАС ВОДА ДЕТСКАЯ 0,6Л, Н/ГАЗ, [STELMAS] | B8: 44721 | C8: 1 | D8: 24.2 | E8: 40
A9: ТИЗИН КЛАССИК 0,1% 10МЛ, НАЗАЛ,СПРЕЙ ФЛ, /ДЖОНСОН/ | B9: 44721 | C9: 1 | D9: 88.43 | E9: 110
A10: ГЛИЦИН 100МГ, №100 ТАБ, ПОДЪЯЗЫЧ, /БИОТИКИ/ | B10: 44721 | C10: 1 | D10: 56.98 | E10: 72
A11: ЛЮКСПЛАСТ ЛЕЙКОПЛАСТ, БАКТЕР, 19Х72ММ ТКАН, ЭЛ,ТЕЛЕСН, №10 [LUXPLAST] | B11: 44721 | C11: 1 | D11: 47.67 | E11: 77
A12: МИГ 400МГ, №20 ТАБ, П/П/О /БЕРЛИН-ХЕМИ/ | B12: 44721 | C12: 1 | D12: 119.06 | E12: 146
A13: ФОСФАЛЮГЕЛЬ 16Г, №20 ГЕЛЬ Д/ПРИЕМА ВНУТРЬ ПАК, | B13: 44721 | C13: 1 | D13: 429.41 | E13: 580
A14: ЕССЕНТУКИ ВОДА МИНЕР, №4 0,45Л, ГАЗ, СТЕКЛО | B14: 44721 | C14: 1 | D14: 50.1 | E14: 81
A15: АСКОРУТИН 50МГ,+50МГ, №50 ТАБ, /ФАРМСТАНДАРТ-УФИМСКИЙ/ | B15: 44721 | C15: 1 | D15: 34.51 | E15: 54
... A13764: ВАЛИДОЛ 60МГ, №10 ТАБ, ПОДЪЯЗЫЧ, /ФАРМСТАНДАРТ/ | B13764: 44682 | C13764: 1 | D13764: 32.01 | E13764: 37

Sheet Покупки по дням
B2: name | C2: 44682 | D2: 44683 | E2: 44684 | F2: 44685 | G2: 44686 | H2: 44687 | I2: 44688 | J2: 44689 | K2: 44690 | L2: 44691 | M2: 44692 | N2: 44693 | O2: 44694 | P2: 44695 | Q2: 44696 | R2: 44697 | S2: 44698 | T2: 44699 | U2: 44700 | V2: 44701 | W2: 44702 | X2: 44703 | Y2: 44704 | Z2: 44705 | AA2: 44706 | AB2: 44707 | AC2: 44708 | AD2: 44709 | AE2: 44710 | AF2: 44711 | AG2: 44712 | AH2: 44713 | AI2: 44714 | AJ2: 44715 | AK2: 44716 | AL2: 44717 | AM2: 44718 | AN2: 44719 | AO2: 44720 | AP2: 44721 | AQ2: var
B3: ЛЮКСПЛАСТ ЛЕЙКОПЛАСТ, БАКТЕР, 19Х72ММ ТКАН, ЭЛ,ТЕЛЕСН, №10 [LUXPLAST] | C3: =SUMIFS(data!$C:$C,data!$A:$A,"="&'Покупки по дням'!$B3,data!$B:$B,"="&'Покупки по дням'!C$2) -> 0 | D3: =SUMIFS(data!$C:$C,data!$A:$A,"="&'Покупки по дням'!$B3,data!$B:$B,"="&'Покупки по дням'!D$2) -> 2 | E3: =SUMIFS(data!$C:$C,data!$A:$A,"="&'Покупки по дням'!$B3,data!$B:$B,"="&'Покупки по дням'!E$2) -> 3 | F3: =SUMIFS(data!$C:$C,data!$A:$A,"="&'Покупки по дням'!$B3,data!$B:$B,"="&'Покупки по дням'!F$2) -> 0 | G3: =SUMIFS(data!$C:$C,data!$A:$A,"="&'Покупки по дням'!$B3,data!$B:$B,"="&'Покупки по дням'!G$2) -> 2 | H3: =SUMIFS(data!$C:$C,data!$A:$A,"="&'Покупки по дням'!$B3,data!$B:$B,"="&'Покупки по дням'!H$2) -> 7 | I3: =SUMIFS(data!$C:$C,data!$A:$A,"="&'Покупки по дням'!$B3,data!$B:$B,"="&'Покупки по дням'!I$2) -> 6 | J3: =SUMIFS(data!$C:$C,data!$A:$A,"="&'Покупки по дням'!$B3,data!$B:$B,"="&'Покупки по дням'!J$2) -> 3 | ... AP3: =SUMIFS(data!$C:$C,data!$A:$A,"="&'Покупки по дням'!$B3,data!$B:$B,"="&'Покупки по дням'!AP$2) -> 11 | AQ3: =_xlfn.STDEV.S(C3:AP3)/AVERAGE(C3:AP3) -> 0.84514713
B4: УГОЛЬ АКТИВИРОВАННЫЙ 250МГ, №50 ТАБ, /ФАРМСТАНДАРТ ЛЕКСРЕДСТВА/ | C4: =SUMIFS(data!$C:$C,data!$A:$A,"="&'Покупки по дням'!$B4,data!$B:$B,"="&'Покупки по дням'!C$2) -> 4 | D4: =SUMIFS(data!$C:$C,data!$A:$A,"="&'Покупки по дням'!$B4,data!$B:$B,"="&'Покупки по дням'!D$2) -> 0 | E4: =SUMIFS(data!$C:$C,data!$A:$A,"="&'Покупки по дням'!$B4,data!$B:$B,"="&'Покупки по дням'!E$2) -> 3 | F4: =SUMIFS(data!$C:$C,data!$A:$A,"="&'Покупки по дням'!$B4,data!$B:$B,"="&'Покупки по дням'!F$2) -> 7 | G4: =SUMIFS(data!$C:$C,data!$A:$A,"="&'Покупки по дням'!$B4,data!$B:$B,"="&'Покупки по дням'!G$2) -> 6 | H4: =SUMIFS(data!$C:$C,data!$A:$A,"="&'Покупки по дням'!$B4,data!$B:$B,"="&'Покупки по дням'!H$2) -> 6 | I4: =SUMIFS(data!$C:$C,data!$A:$A,"="&'Покупки по дням'!$B4,data!$B:$B,"="&'Покупки по дням'!I$2) -> 7 | J4: =SUMIFS(data!$C:$C,data!$A:$A,"="&'Покупки по дням'!$B4,data!$B:$B,"="&'Покупки по дням'!J$2) -> 5 | ... AP4: =SUMIFS(data!$C:$C,data!$A:$A,"="&'Покупки по дням'!$B4,data!$B:$B,"="&'Покупки по дням'!AP$2) -> 2 | AQ4: =_xlfn.STDEV.S(C4:AP4)/AVERAGE(C4:AP4) -> 0.63202543
B5: ЦИТРАМОН П №20 ТАБ, /ФАРМСТАНДАРТ/ | C5: =SUMIFS(data!$C:$C,data!$A:$A,"="&'Покупки по дням'!$B5,data!$B:$B,"="&'Покупки по дням'!C$2) -> 7 | D5: =SUMIFS(data!$C:$C,data!$A:$A,"="&'Покупки по дням'!$B5,data!$B:$B,"="&'Покупки по дням'!D$2) -> 7 | E5: =SUMIFS(data!$C:$C,data!$A:$A,"="&'Покупки по дням'!$B5,data!$B:$B,"="&'Покупки по дням'!E$2) -> 6 | F5: =SUMIFS(data!$C:$C,data!$A:$A,"="&'Покупки по дням'!$B5,data!$B:$B,"="&'Покупки по дням'!F$2) -> 5 | G5: =SUMIFS(data!$C:$C,data!$A:$A,"="&'Покупки по дням'!$B5,data!$B:$B,"="&'Покупки по дням'!G$2) -> 4 | H5: =SUMIFS(data!$C:$C,data!$A:$A,"="&'Покупки по дням'!$B5,data!$B:$B,"="&'Покупки по дням'!H$2) -> 5 | I5: =SUMIFS(data!$C:$C,data!$A:$A,"="&'Покупки по дням'!$B5,data!$B:$B,"="&'Покупки по дням'!I$2) -> 3 | J5: =SUMIFS(data!$C:$C,data!$A:$A,"="&'Покупки по дням'!$B5,data!$B:$B,"="&'Покупки по дням'!J$2) -> 3 | ... AP5: =SUMIFS(data!$C:$C,data!$A:$A,"="&'Покупки по дням'!$B5,data!$B:$B,"="&'Покупки по дням'!AP$2) -> 1 | AQ5: =_xlfn.STDEV.S(C5:AP5)/AVERAGE(C5:AP5) -> 0.61817081
B6: ВАЛЕРИАНА ЭКСТРАКТ 20МГ, №50 ТАБ, П/О /БОРИСОВСКИЙ/ | C6: =SUMIFS(data!$C:$C,data!$A:$A,"="&'Покупки по дням'!$B6,data!$B:$B,"="&'Покупки по дням'!C$2) -> 1 | D6: =SUMIFS(data!$C:$C,data!$A:$A,"="&'Покупки по дням'!$B6,data!$B:$B,"="&'Покупки по дням'!D$2) -> 4 | E6: =SUMIFS(data!$C:$C,data!$A:$A,"="&'Покупки по дням'!$B6,data!$B:$B,"="&'Покупки по дням'!E$2) -> 4 | F6: =SUMIFS(data!$C:$C,data!$A:$A,"="&'Покупки по дням'!$B6,data!$B:$B,"="&'Покупки по дням'!F$2) -> 1 | G6: =SUMIFS(data!$C:$C,data!$A:$A,"="&'Покупки по дням'!$B6,data!$B:$B,"="&'Покупки по дням'!G$2) -> 4 | H6: =SUMIFS(data!$C:$C,data!$A:$A,"="&'Покупки по дням'!$B6,data!$B:$B,"="&'Покупки по дням'!H$2) -> 6 | I6: =SUMIFS(data!$C:$C,data!$A:$A,"="&'Покупки по дням'!$B6,data!$B:$B,"="&'Покупки по дням'!I$2) -> 6 | J6: =SUMIFS(data!$C:$C,data!$A:$A,"="&'Покупки по дням'!$B6,data!$B:$B,"="&'Покупки по дням'!J$2) -> 0 | ... AP6: =SUMIFS(data!$C:$C,data!$A:$A,"="&'Покупки по дням'!$B6,data!$B:$B,"="&'Покупки по дням'!AP$2) -> 3 | AQ6: =_xlfn.STDEV.S(C6:AP6)/AVERAGE(C6:AP6) -> 0.61844536
B7: СФМ ШПРИЦ 2МЛ, 3-Х КОМП, 0,63Х32ММ 23G №10 [SFM] | C7: =SUMIFS(data!$C:$C,data!$A:$A,"="&'Покупки по дням'!$B7,data!$B:$B,"="&'Покупки по дням'!C$2) -> 1 | D7: =SUMIFS(data!$C:$C,data!$A:$A,"="&'Покупки по дням'!$B7,data!$B:$B,"="&'Покупки по дням'!D$2) -> 2 | E7: =SUMIFS(data!$C:$C,data!$A:$A,"="&'Покупки по дням'!$B7,data!$B:$B,"="&'Покупки по дням'!E$2) -> 0 | F7: =SUMIFS(data!$C:$C,data!$A:$A,"="&'Покупки по дням'!$B7,data!$B:$B,"="&'Покупки по дням'!F$2) -> 1 | G7: =SUMIFS(data!$C:$C,data!$A:$A,"="&'Покупки по дням'!$B7,data!$B:$B,"="&'Покупки по дням'!G$2) -> 1 | H7: =SUMIFS(data!$C:$C,data!$A:$A,"="&'Покупки по дням'!$B7,data!$B:$B,"="&'Покупки по дням'!H$2) -> 3 | I7: =SUMIFS(data!$C:$C,data!$A:$A,"="&'Покупки по дням'!$B7,data!$B:$B,"="&'Покупки по дням'!I$2) -> 2 | J7: =SUMIFS(data!$C:$C,data!$A:$A,"="&'Покупки по дням'!$B7,data!$B:$B,"="&'Покупки по дням'!J$2) -> 0 | ... AP7: =SUMIFS(data!$C:$C,data!$A:$A,"="&'Покупки по дням'!$B7,data!$B:$B,"="&'Покупки по дням'!AP$2) -> 1.5 | AQ7: =_xlfn.STDEV.S(C7:AP7)/AVERAGE(C7:AP7) -> 0.7195565
B8: СФМ ШПРИЦ 5МЛ, 3-Х КОМП, 0,7Х40ММ 22G №10 [SFM] | C8: =SUMIFS(data!$C:$C,data!$A:$A,"="&'Покупки по дням'!$B8,data!$B:$B,"="&'Покупки по дням'!C$2) -> 2.1 | D8: =SUMIFS(data!$C:$C,data!$A:$A,"="&'Покупки по дням'!$B8,data!$B:$B,"="&'Покупки по дням'!D$2) -> 2.3 | E8: =SUMIFS(data!$C:$C,data!$A:$A,"="&'Покупки по дням'!$B8,data!$B:$B,"="&'Покупки по дням'!E$2) -> 5.2 | F8: =SUMIFS(data!$C:$C,data!$A:$A,"="&'Покупки по дням'!$B8,data!$B:$B,"="&'Покупки по дням'!F$2) -> 5.3 | G8: =SUMIFS(data!$C:$C,data!$A:$A,"="&'Покупки по дням'!$B8,data!$B:$B,"="&'Покупки по дням'!G$2) -> 3 | H8: =SUMIFS(data!$C:$C,data!$A:$A,"="&'Покупки по дням'!$B8,data!$B:$B,"="&'Покупки по дням'!H$2) -> 1 | I8: =SUMIFS(data!$C:$C,data!$A:$A,"="&'Покупки по дням'!$B8,data!$B:$B,"="&'Покупки по дням'!I$2) -> 4.2 | J8: =SUMIFS(data!$C:$C,data!$A:$A,"="&'Покупки по дням'!$B8,data!$B:$B,"="&'Покупки по дням'!J$2) -> 1.1 | ... AP8: =SUMIFS(data!$C:$C,data!$A:$A,"="&'Покупки по дням'!$B8,data!$B:$B,"="&'Покупки по дням'!AP$2) -> 1.6 | AQ8: =_xlfn.STDEV.S(C8:AP8)/AVERAGE(C8:AP8) -> 0.52749727
B9: КЕТОРОЛ ЭКСПРЕСС 10МГ, №20 ТАБ, ДИСПЕРГ, /Д-Р РЕДДИС/ | C9: =SUMIFS(data!$C:$C,data!$A:$A,"="&'Покупки по дням'!$B9,data!$B:$B,"="&'Покупки по дням'!C$2) -> 3 | D9: =SUMIFS(data!$C:$C,data!$A:$A,"="&'Покупки по дням'!$B9,data!$B:$B,"="&'Покупки по дням'!D$2) -> 1 | E9: =SUMIFS(data!$C:$C,data!$A:$A,"="&'Покупки по дням'!$B9,data!$B:$B,"="&'Покупки по дням'!E$2) -> 1 | F9: =SUMIFS(data!$C:$C,data!$A:$A,"="&'Покупки по дням'!$B9,data!$B:$B,"="&'Покупки по дням'!F$2) -> 12 | G9: =SUMIFS(data!$C:$C,data!$A:$A,"="&'Покупки по дням'!$B9,data!$B:$B,"="&'Покупки по дням'!G$2) -> 8 | H9: =SUMIFS(data!$C:$C,data!$A:$A,"="&'Покупки по дням'!$B9,data!$B:$B,"="&'Покупки по дням'!H$2) -> 5 | I9: =SUMIFS(data!$C:$C,data!$A:$A,"="&'Покупки по дням'!$B9,data!$B:$B,"="&'Покупки по дням'!I$2) -> 5 | J9: =SUMIFS(data!$C:$C,data!$A:$A,"="&'Покупки по дням'!$B9,data!$B:$B,"="&'Покупки по дням'!J$2) -> 4 | ... AP9: =SUMIFS(data!$C:$C,data!$A:$A,"="&'Покупки по дням'!$B9,data!$B:$B,"="&'Покупки по дням'!AP$2) -> 2 | AQ9: =_xlfn.STDEV.S(C9:AP9)/AVERAGE(C9:AP9) -> 0.6886848
B10: РОМАШКИ ЦВЕТКИ 1,5Г, №20 ПАК, /КРАСНОГОРСК/ | C10: =SUMIFS(data!$C:$C,data!$A:$A,"="&'Покупки по дням'!$B10,data!$B:$B,"="&'Покупки по дням'!C$2) -> 7 | D10: =SUMIFS(data!$C:$C,data!$A:$A,"="&'Покупки по дням'!$B10,data!$B:$B,"="&'Покупки по дням'!D$2) -> 4 | E10: =SUMIFS(data!$C:$C,data!$A:$A,"="&'Покупки по дням'!$B10,data!$B:$B,"="&'Покупки по дням'!E$2) -> 3 | F10: =SUMIFS(data!$C:$C,data!$A:$A,"="&'Покупки по дням'!$B10,data!$B:$B,"="&'Покупки по дням'!F$2) -> 5 | G10: =SUMIFS(data!$C:$C,data!$A:$A,"="&'Покупки по дням'!$B10,data!$B:$B,"="&'Покупки по дням'!G$2) -> 5 | H10: =SUMIFS(data!$C:$C,data!$A:$A,"="&'Покупки по дням'!$B10,data!$B:$B,"="&'Покупки по дням'!H$2) -> 4 | I10: =SUMIFS(data!$C:$C,data!$A:$A,"="&'Покупки по дням'!$B10,data!$B:$B,"="&'Покупки по дням'!I$2) -> 3 | J10: =SUMIFS(data!$C:$C,data!$A:$A,"="&'Покупки по дням'!$B10,data!$B:$B,"="&'Покупки по дням'!J$2) -> 3 | ... AP10: =SUMIFS(data!$C:$C,data!$A:$A,"="&'Покупки по дням'!$B10,data!$B:$B,"="&'Покупки по дням'!AP$2) -> 1 | AQ10: =_xlfn.STDEV.S(C10:AP10)/AVERAGE(C10:AP10) -> 0.61168835
B11: ЛЕВОМЕКОЛЬ 40МГ/Г,+7,5МГ/Г, 40Г, №1 МАЗЬ Д/НАРУЖ,ПРИМ, ТУБА /НИЖФАРМ/ | C11: =SUMIFS(data!$C:$C,data!$A:$A,"="&'Покупки по дням'!$B11,data!$B:$B,"="&'Покупки по дням'!C$2) -> 2 | D11: =SUMIFS(data!$C:$C,data!$A:$A,"="&'Покупки по дням'!$B11,data!$B:$B,"="&'Покупки по дням'!D$2) -> 5 | E11: =SUMIFS(data!$C:$C,data!$A:$A,"="&'Покупки по дням'!$B11,data!$B:$B,"="&'Покупки по дням'!E$2) -> 2 | F11: =SUMIFS(data!$C:$C,data!$A:$A,"="&'Покупки по дням'!$B11,data!$B:$B,"="&'Покупки по дням'!F$2) -> 3 | G11: =SUMIFS(data!$C:$C,data!$A:$A,"="&'Покупки по дням'!$B11,data!$B:$B,"="&'Покупки по дням'!G$2) -> 4 | H11: =SUMIFS(data!$C:$C,data!$A:$A,"="&'Покупки по дням'!$B11,data!$B:$B,"="&'Покупки по дням'!H$2) -> 2 | I11: =SUMIFS(data!$C:$C,data!$A:$A,"="&'Покупки по дням'!$B11,data!$B:$B,"="&'Покупки по дням'!I$2) -> 7 | J11: =SUMIFS(data!$C:$C,data!$A:$A,"="&'Покупки по дням'!$B11,data!$B:$B,"="&'Покупки по дням'!J$2) -> 2 | ... AP11: =SUMIFS(data!$C:$C,data!$A:$A,"="&'Покупки по дням'!$B11,data!$B:$B,"="&'Покупки по дням'!AP$2) -> 2 | AQ11: =_xlfn.STDEV.S(C11:AP11)/AVERAGE(C11:AP11) -> 0.69066764
B12: ИНГАЛИПТ 30МЛ, АЭРОЗОЛЬ Д/МЕСТ,ПРИМ, БАЛЛОН /ФАРМСТАНДАРТ-ЛЕКСРЕДСТВА/ | C12: =SUMIFS(data!$C:$C,data!$A:$A,"="&'Покупки по дням'!$B12,data!$B:$B,"="&'Покупки по дням'!C$2) -> 2 | D12: =SUMIFS(data!$C:$C,data!$A:$A,"="&'Покупки по дням'!$B12,data!$B:$B,"="&'Покупки по дням'!D$2) -> 2 | E12: =SUMIFS(data!$C:$C,data!$A:$A,"="&'Покупки по дням'!$B12,data!$B:$B,"="&'Покупки по дням'!E$2) -> 1 | F12: =SUMIFS(data!$C:$C,data!$A:$A,"="&'Покупки по дням'!$B12,data!$B:$B,"="&'Покупки по дням'!F$2) -> 2 | G12: =SUMIFS(data!$C:$C,data!$A:$A,"="&'Покупки по дням'!$B12,data!$B:$B,"="&'Покупки по дням'!G$2) -> 1 | H12: =SUMIFS(data!$C:$C,data!$A:$A,"="&'Покупки по дням'!$B12,data!$B:$B,"="&'Покупки по дням'!H$2) -> 4 | I12: =SUMIFS(data!$C:$C,data!$A:$A,"="&'Покупки по дням'!$B12,data!$B:$B,"="&'Покупки по дням'!I$2) -> 2 | J12: =SUMIFS(data!$C:$C,data!$A:$A,"="&'Покупки по дням'!$B12,data!$B:$B,"="&'Покупки по дням'!J$2) -> 2 | ... AP12: =SUMIFS(data!$C:$C,data!$A:$A,"="&'Покупки по дням'!$B12,data!$B:$B,"="&'Покупки по дням'!AP$2) -> 0 | AQ12: =_xlfn.STDEV.S(C12:AP12)/AVERAGE(C12:AP12) -> 0.746417
B13: СПАЗМАЛГОН №20 ТАБ, | C13: =SUMIFS(data!$C:$C,data!$A:$A,"="&'Покупки по дням'!$B13,data!$B:$B,"="&'Покупки по дням'!C$2) -> 5 | D13: =SUMIFS(data!$C:$C,data!$A:$A,"="&'Покупки по дням'!$B13,data!$B:$B,"="&'Покупки по дням'!D$2) -> 1 | E13: =SUMIFS(data!$C:$C,data!$A:$A,"="&'Покупки по дням'!$B13,data!$B:$B,"="&'Покупки по дням'!E$2) -> 2 | F13: =SUMIFS(data!$C:$C,data!$A:$A,"="&'Покупки по дням'!$B13,data!$B:$B,"="&'Покупки по дням'!F$2) -> 1 | G13: =SUMIFS(data!$C:$C,data!$A:$A,"="&'Покупки по дням'!$B13,data!$B:$B,"="&'Покупки по дням'!G$2) -> 2 | H13: =SUMIFS(data!$C:$C,data!$A:$A,"="&'Покупки по дням'!$B13,data!$B:$B,"="&'Покупки по дням'!H$2) -> 2 | I13: =SUMIFS(data!$C:$C,data!$A:$A,"="&'Покупки по дням'!$B13,data!$B:$B,"="&'Покупки по дням'!I$2) -> 1 | J13: =SUMIFS(data!$C:$C,data!$A:$A,"="&'Покупки по дням'!$B13,data!$B:$B,"="&'Покупки по дням'!J$2) -> 2 | ... AP13: =SUMIFS(data!$C:$C,data!$A:$A,"="&'Покупки по дням'!$B13,data!$B:$B,"="&'Покупки по дням'!AP$2) -> 3 | AQ13: =_xlfn.STDEV.S(C13:AP13)/AVERAGE(C13:AP13) -> 0.6937732
B14: ИБУКЛИН 400МГ,+325МГ, №10 ТАБ, П/П/О | C14: =SUMIFS(data!$C:$C,data!$A:$A,"="&'Покупки по дням'!$B14,data!$B:$B,"="&'Покупки по дням'!C$2) -> 0 | D14: =SUMIFS(data!$C:$C,data!$A:$A,"="&'Покупки по дням'!$B14,data!$B:$B,"="&'Покупки по дням'!D$2) -> 1 | E14: =SUMIFS(data!$C:$C,data!$A:$A,"="&'Покупки по дням'!$B14,data!$B:$B,"="&'Покупки по дням'!E$2) -> 2 | F14: =SUMIFS(data!$C:$C,data!$A:$A,"="&'Покупки по дням'!$B14,data!$B:$B,"="&'Покупки по дням'!F$2) -> 0 | G14: =SUMIFS(data!$C:$C,data!$A:$A,"="&'Покупки по дням'!$B14,data!$B:$B,"="&'Покупки по дням'!G$2) -> 0 | H14: =SUMIFS(data!$C:$C,data!$A:$A,"="&'Покупки по дням'!$B14,data!$B:$B,"="&'Покупки по дням'!H$2) -> 3 | I14: =SUMIFS(data!$C:$C,data!$A:$A,"="&'Покупки по дням'!$B14,data!$B:$B,"="&'Покупки по дням'!I$2) -> 3 | J14: =SUMIFS(data!$C:$C,data!$A:$A,"="&'Покупки по дням'!$B14,data!$B:$B,"="&'Покупки по дням'!J$2) -> 0 | ... AP14: =SUMIFS(data!$C:$C,data!$A:$A,"="&'Покупки по дням'!$B14,data!$B:$B,"="&'Покупки по дням'!AP$2) -> 1 | AQ14: =_xlfn.STDEV.S(C14:AP14)/AVERAGE(C14:AP14) -> 1.0418874
... B158: ТРИХОПОЛ 250МГ, №20 ТАБ, /ПОЛЬФАРМА/ | C158: =SUMIFS(data!$C:$C,data!$A:$A,"="&'Покупки по дням'!$B158,data!$B:$B,"="&'Покупки по дням'!C$2) -> 0 | D158: =SUMIFS(data!$C:$C,data!$A:$A,"="&'Покупки по дням'!$B158,data!$B:$B,"="&'Покупки по дням'!D$2) -> 2 | E158: =SUMIFS(data!$C:$C,data!$A:$A,"="&'Покупки по дням'!$B158,data!$B:$B,"="&'Покупки по дням'!E$2) -> 0 | F158: =SUMIFS(data!$C:$C,data!$A:$A,"="&'Покупки по дням'!$B158,data!$B:$B,"="&'Покупки по дням'!F$2) -> 2 | G158: =SUMIFS(data!$C:$C,data!$A:$A,"="&'Покупки по дням'!$B158,data!$B:$B,"="&'Покупки по дням'!G$2) -> 0 | H158: =SUMIFS(data!$C:$C,data!$A:$A,"="&'Покупки по дням'!$B158,data!$B:$B,"="&'Покупки по дням'!H$2) -> 0 | I158: =SUMIFS(data!$C:$C,data!$A:$A,"="&'Покупки по дням'!$B158,data!$B:$B,"="&'Покупки по дням'!I$2) -> 1 | J158: =SUMIFS(data!$C:$C,data!$A:$A,"="&'Покупки по дням'!$B158,data!$B:$B,"="&'Покупки по дням'!J$2) -> 1 | ... AP158: =SUMIFS(data!$C:$C,data!$A:$A,"="&'Покупки по дням'!$B158,data!$B:$B,"="&'Покупки по дням'!AP$2) -> 2 | AQ158: =_xlfn.STDEV.S(C158:AP158)/AVERAGE(C158:AP158) -> 1.1998411

Sheet сводник по ABC
A3: Названия строк | B3: Сумма по полю dr_kol | C3: Сумма по полю dr_czak | D3: Сумма по полю dr_croz
A4: L-ТИРОКСИН 50МКГ, №50 ТАБ, /БЕРЛИН ХЕМИ/ | B4: 45 | C4: 3933.7 | D4: 4598
A5: АКВАДЕТРИМ 15000МЕ/МЛ, 10МЛ, КАПЛИ Д/ПРИЕМА ВНУТРЬ ФЛ,/КАП, (ВИТАМИН Д3 ВОДН,Р-Р) /МЕДАНА/ | B5: 43 | C5: 7053.69 | D5: 8342.02
A6: АЛЛОХОЛ №50 ТАБ, П/О /ФАРМСТАНДАРТ/ | B6: 49 | C6: 2350.61 | D6: 3578
A7: АММИАК 100МГ/МЛ, 100МЛ, №1 Р-Р Д/НАРУЖ,/ИНГ, ФЛ, /САМАРСКАЯ ФФ/ | B7: 165 | C7: 2645.2 | D7: 4177
A8: АНАЛЬГИН 500МГ, №20 ТАБ, /ФАРМСТАНДАРТ/ | B8: 115 | C8: 4234.6 | D8: 6551
A9: АСЕПТИКА САЛФЕТКА СПИРТОВАЯ 60Х100 №20 | B9: 97.95 | C9: 3180.74 | D9: 5289
A10: АСЕПТИКА САЛФЕТКА СПИРТОВАЯ 60Х100 №30 | B10: 88 | C10: 3272.91 | D10: 5311
A11: АСКОРБИНОВАЯ К-ТА 100МГ,+877МГ, ГЛЮКОЗА №40 ТАБ, /ФАРМСТАНДАРТ/ | B11: 45 | C11: 1449.02 | D11: 2273
A12: АСКОРБИНОВАЯ К-ТА 25МГ, №10 ТАБ, КРУТКА САХ, (БАД) | B12: 142 | C12: 1188 | D12: 1997
A13: АСКОРБИНОВАЯ К-ТА 50МГ, №200 ДРАЖЕ /ФАРМСТАНДАРТ-УФАВИТА/ | B13: 51 | C13: 997.38 | D13: 1209
A14: АСКОРБИНОВАЯ К-ТА АПЕЛЬСИН №10 ТАБ, КРУТКА САХ, | B14: 70 | C14: 431.67 | D14: 722
A15: АСКОРУТИН 50МГ,+50МГ, №50 ТАБ, /ФАРМСТАНДАРТ-УФИМСКИЙ/ | B15: 48 | C15: 2062.03 | D15: 3207
... A160: Общий итог | B160: 15620.108 | C160: 1558844.8 | D160: 2006310.3

Sheet ABC
A1: name | B1: kol | C1: zak | D1: roz | E1: perc_kol | F1: cumsum_kol | G1: margin | H1: abc_kol | I1: perc_roz | J1: cumsum_roz | K1: abc_roz | M1: perc_margin | N1: cumsum_margin | O1: abc_margin | P1: ABC | Q1: var | R1: XYZ | S1: ABC-XYZ
A2: ЛЮКСПЛАСТ ЛЕЙКОПЛАСТ, БАКТЕР, 19Х72ММ ТКАН, ЭЛ,ТЕЛЕСН, №10 [LUXPLAST] | B2: 151 | C2: 5975.18 | D2: 9692 | E2: 0.0096670266 | F2: 0.42502907 | G2: 0.3834936 | H2: A | I2: 0.0048307583 | J2: 0.79458725 | K2: A | M2: 0.0097256527 | N2: 0.19150033 | O2: A | P2: =H2&K2&O2 -> AAA | Q2: =VLOOKUP(A2,xyz!A:AQ,2,FALSE) -> 0.67615894 | R2: =IF(Q2<0.1,"X",IF(Q2<0.25,"Y","Z")) -> Z | S2: =P2&R2 -> AAAZ
A3: УГОЛЬ АКТИВИРОВАННЫЙ 250МГ, №50 ТАБ, /ФАРМСТАНДАРТ ЛЕКСРЕДСТВА/ | B3: 179 | C3: 7147.68 | D3: 11109 | E3: 0.011459588 | F3: 0.34103477 | G3: 0.35658655 | H3: A | I3: 0.0055370299 | J3: 0.76418103 | K3: A | M3: 0.009043272 | N3: 0.31183028 | O3: A | P3: =H3&K3&O3 -> AAA | Q3: =VLOOKUP(A3,xyz!A:AQ,2,FALSE) -> 0.49134078 | R3: =IF(Q3<0.1,"X",IF(Q3<0.25,"Y","Z")) -> Z | S3: =P3&R3 -> AAAZ
A4: ЦИТРАМОН П №20 ТАБ, /ФАРМСТАНДАРТ/ | B4: 173 | C4: 7460.08 | D4: 11585 | E4: 0.011075468 | F4: 0.36350581 | G4: 0.35605697 | H4: A | I4: 0.0057742813 | J4: 0.75292853 | K4: A | M4: 0.0090298414 | N4: 0.32086013 | O4: A | P4: =H4&K4&O4 -> AAA | Q4: =VLOOKUP(A4,xyz!A:AQ,2,FALSE) -> 0.52196532 | R4: =IF(Q4<0.1,"X",IF(Q4<0.25,"Y","Z")) -> Z | S4: =P4&R4 -> AAAZ
A5: ВАЛЕРИАНА ЭКСТРАКТ 20МГ, №50 ТАБ, П/О /БОРИСОВСКИЙ/ | B5: 154 | C5: 6918.05 | D5: 10742 | E5: 0.0098590867 | F5: 0.41536204 | G5: 0.3559812 | H5: A | I5: 0.005354107 | J5: 0.76953513 | K5: A | M5: 0.0090279197 | N5: 0.32988804 | O5: A | P5: =H5&K5&O5 -> AAA | Q5: =VLOOKUP(A5,xyz!A:AQ,2,FALSE) -> 0.48051948 | R5: =IF(Q5<0.1,"X",IF(Q5<0.25,"Y","Z")) -> Z | S5: =P5&R5 -> AAAZ
A6: СФМ ШПРИЦ 2МЛ, 3-Х КОМП, 0,63Х32ММ 23G №10 [SFM] | B6: 78.1 | C6: 10120.01 | D6: 15669.55 | E6: 0.0049999654 | F6: 0.71809042 | G6: 0.35416078 | H6: A | I6: 0.0078101329 | J6: 0.67375554 | K6: A | M6: 0.0089817527 | N6: 0.36588028 | O6: A | P6: =H6&K6&O6 -> AAA | Q6: =VLOOKUP(A6,xyz!A:AQ,2,FALSE) -> 0.54795134 | R6: =IF(Q6<0.1,"X",IF(Q6<0.25,"Y","Z")) -> Z | S6: =P6&R6 -> AAAZ
A7: СФМ ШПРИЦ 5МЛ, 3-Х КОМП, 0,7Х40ММ 22G №10 [SFM] | B7: 115.6 | C7: 17169.07 | D7: 26582 | E7: 0.007400717 | F7: 0.54869018 | G7: 0.35410917 | H7: A | I7: 0.013249197 | J7: 0.50313592 | K7: A | M7: 0.008980444 | N7: 0.37486072 | O7: A | P7: =H7&K7&O7 -> AAA | Q7: =VLOOKUP(A7,xyz!A:AQ,2,FALSE) -> 0.44602076 | R7: =IF(Q7<0.1,"X",IF(Q7<0.25,"Y","Z")) -> Z | S7: =P7&R7 -> AAAZ
A8: КЕТОРОЛ ЭКСПРЕСС 10МГ, №20 ТАБ, ДИСПЕРГ, /Д-Р РЕДДИС/ | B8: 194 | C8: 8596.1 | D8: 13278 | E8: 0.012419888 | F8: 0.293852 | G8: 0.35260581 | H8: A | I8: 0.0066181189 | J8: 0.71609147 | K8: A | M8: 0.0089423178 | N8: 0.39277044 | O8: A | P8: =H8&K8&O8 -> AAA | Q8: =VLOOKUP(A8,xyz!A:AQ,2,FALSE) -> 0.51391753 | R8: =IF(Q8<0.1,"X",IF(Q8<0.25,"Y","Z")) -> Z | S8: =P8&R8 -> AAAZ
A9: РОМАШКИ ЦВЕТКИ 1,5Г, №20 ПАК, /КРАСНОГОРСК/ | B9: 142 | C9: 10064.98 | D9: 14512 | E9: 0.0090908462 | F9: 0.45262171 | G9: 0.30643743 | H9: A | I9: 0.0072331783 | J9: 0.68860668 | K9: A | M9: 0.0077714569 | N9: 0.49175547 | O9: A | P9: =H9&K9&O9 -> AAA | Q9: =VLOOKUP(A9,xyz!A:AQ,2,FALSE) -> 0.44577465 | R9: =IF(Q9<0.1,"X",IF(Q9<0.25,"Y","Z")) -> Z | S9: =P9&R9 -> AAAZ
A10: ЛЕВОМЕКОЛЬ 40МГ/Г,+7,5МГ/Г, 40Г, №1 МАЗЬ Д/НАРУЖ,ПРИМ, ТУБА /НИЖФАРМ/ | B10: 118 | C10: 17345.1 | D10: 24172 | E10: 0.0075543651 | F10: 0.52630878 | G10: 0.28243008 | H10: A | I10: 0.012047987 | J10: 0.52784446 | K10: A | M10: 0.0071626147 | N10: 0.51425745 | O10: A | P10: =H10&K10&O10 -> AAA | Q10: =VLOOKUP(A10,xyz!A:AQ,2,FALSE) -> 0.52542373 | R10: =IF(Q10<0.1,"X",IF(Q10<0.25,"Y","Z")) -> Z | S10: =P10&R10 -> AAAZ
A11: ИНГАЛИПТ 30МЛ, АЭРОЗОЛЬ Д/МЕСТ,ПРИМ, БАЛЛОН /ФАРМСТАНДАРТ-ЛЕКСРЕДСТВА/ | B11: 72 | C11: 8670.44 | D11: 12055 | E11: 0.0046094431 | F11: 0.73702755 | G11: 0.28075985 | H11: A | I11: 0.0060085422 | J11: 0.74124756 | K11: A | M11: 0.0071202564 | N11: 0.5213777 | O11: A | P11: =H11&K11&O11 -> AAA | Q11: =VLOOKUP(A11,xyz!A:AQ,2,FALSE) -> 0.62222222 | R11: =IF(Q11<0.1,"X",IF(Q11<0.25,"Y","Z")) -> Z | S11: =P11&R11 -> AAAZ
A12: СПАЗМАЛГОН №20 ТАБ, | B12: 81 | C12: 14922.95 | D12: 20729 | E12: 0.0051856235 | F12: 0.70291127 | G12: 0.28009311 | H12: A | I12: 0.010331901 | J12: 0.59428864 | K12: A | M12: 0.0071033473 | N12: 0.53558655 | O12: A | P12: =H12&K12&O12 -> AAA | Q12: =VLOOKUP(A12,xyz!A:AQ,2,FALSE) -> 0.5345679 | R12: =IF(Q12<0.1,"X",IF(Q12<0.25,"Y","Z")) -> Z | S12: =P12&R12 -> AAAZ
A13: ИБУКЛИН 400МГ,+325МГ, №10 ТАБ, П/П/О | B13: 69 | C13: 9379.31 | D13: 12954.92 | E13: 0.004417383 | F13: 0.75956261 | G13: 0.27600402 | H13: A | I13: 0.006457087 | J13: 0.72254855 | K13: A | M13: 0.0069996454 | N13: 0.54965908 | O13: A | P13: =H13&K13&O13 -> AAA | Q13: =VLOOKUP(A13,xyz!A:AQ,2,FALSE) -> 0.75217391 | R13: =IF(Q13<0.1,"X",IF(Q13<0.25,"Y","Z")) -> Z | S13: =P13&R13 -> AAAZ
... A157: ТРИХОПОЛ 250МГ, №20 ТАБ, /ПОЛЬФАРМА/ | B157: 42 | C157: 3019.17 | D157: 3706 | E157: 0.0026888418 | F157: 0.9732359 | G157: 0.1853292 | H157: C | I157: 0.0018471719 | J157: 0.95839691 | K157: C | M157: 0.0047000716 | N157: 0.79808945 | O157: B | P157: =H157&K157&O157 -> CCB | Q157: =VLOOKUP(A157,xyz!A:AQ,2,FALSE) -> 0.87619048 | R157: =IF(Q157<0.1,"X",IF(Q157<0.25,"Y","Z")) -> Z | S157: =P157&R157 -> CCBZ

Sheet Сводник по кол-ву ABC-XYZ
A3: Названия строк | B3: Количество по полю group
A4: AAAZ | B4: 13
A5: AABZ | B5: 11
A6: AACZ | B6: 10
A7: ABAZ | B7: 14
A8: ABBZ | B8: 16
A9: ACAZ | B9: 16
A10: ACBZ | B10: 6
A11: ACCZ | B11: 2
A12: BAAZ | B12: 3
A13: BABZ | B13: 7
A14: BACZ | B14: 6
A15: BBAZ | B15: 5
... A28: CCBZ | B28: 3
A29: (пусто)
A30: Общий итог | B30: 156

Sheet группы
A1: group
A2: AAAZ
A3: AAAZ
A4: AAAZ
A5: AAAZ
A6: AAAZ
A7: AAAZ
A8: AAAZ
A9: AAAZ
A10: AAAZ
A11: AAAZ
A12: AAAZ
... A157: CCBZ

Sheet распределение_групп_абс
C1: кол-во, выручка, маржинальность
A3: Названия строк | B3: Количество по полю group
A4: AAA | B4: 13
A5: AAB | B5: 11
A6: AAC | B6: 10
A7: ABA | B7: 14
A8: ABB | B8: 16
A9: ABC | B9: 1
A10: ACA | B10: 16
A11: ACB | B11: 6
A12: ACC | B12: 2
A13: BAA | B13: 3
A14: BAB | B14: 7
A15: BAC | B15: 6
... A29: CCB | B29: 3
A30: (пусто)
A31: Общий итог | B31: 157

Sheet xyz
A2: name | B2: var | C2: 44682 | D2: =C2+1 -> 44683 | E2: =D2+1 -> 44684 | F2: =E2+1 -> 44685 | G2: =F2+1 -> 44686 | H2: =G2+1 -> 44687 | I2: =H2+1 -> 44688 | J2: =I2+1 -> 44689 | K2: =J2+1 -> 44690 | ... AP2: =AO2+1 -> 44721 | AQ2: var
A3: ЛЮКСПЛАСТ ЛЕЙКОПЛАСТ, БАКТЕР, 19Х72ММ ТКАН, ЭЛ,ТЕЛЕСН, №10 [LUXPLAST] | B3: =AVEDEV(C3:AP3)/AVERAGE(C3:AP3) -> 0.67615894 | C3: =SUMIFS(data!$C:$C,data!$A:$A,"="&xyz!$A3,data!$B:$B,"="&xyz!C$2) -> 0 | D3: =SUMIFS(data!$C:$C,data!$A:$A,"="&xyz!$A3,data!$B:$B,"="&xyz!D$2) -> 2 | E3: =SUMIFS(data!$C:$C,data!$A:$A,"="&xyz!$A3,data!$B:$B,"="&xyz!E$2) -> 3 | F3: =SUMIFS(data!$C:$C,data!$A:$A,"="&xyz!$A3,data!$B:$B,"="&xyz!F$2) -> 0 | G3: =SUMIFS(data!$C:$C,data!$A:$A,"="&xyz!$A3,data!$B:$B,"="&xyz!G$2) -> 2 | H3: =SUMIFS(data!$C:$C,data!$A:$A,"="&xyz!$A3,data!$B:$B,"="&xyz!H$2) -> 7 | I3: =SUMIFS(data!$C:$C,data!$A:$A,"="&xyz!$A3,data!$B:$B,"="&xyz!I$2) -> 6 | J3: =SUMIFS(data!$C:$C,data!$A:$A,"="&xyz!$A3,data!$B:$B,"="&xyz!J$2) -> 3 | ... AP3: =SUMIFS(data!$C:$C,data!$A:$A,"="&xyz!$A3,data!$B:$B,"="&xyz!AP$2) -> 11 | AQ3: =_xlfn.STDEV.S(C3:AP3)/AVERAGE(C3:AP3) -> 0.84514713
A4: УГОЛЬ АКТИВИРОВАННЫЙ 250МГ, №50 ТАБ, /ФАРМСТАНДАРТ ЛЕКСРЕДСТВА/ | B4: =AVEDEV(C4:AP4)/AVERAGE(C4:AP4) -> 0.49134078 | C4: =SUMIFS(data!$C:$C,data!$A:$A,"="&xyz!$A4,data!$B:$B,"="&xyz!C$2) -> 4 | D4: =SUMIFS(data!$C:$C,data!$A:$A,"="&xyz!$A4,data!$B:$B,"="&xyz!D$2) -> 0 | E4: =SUMIFS(data!$C:$C,data!$A:$A,"="&xyz!$A4,data!$B:$B,"="&xyz!E$2) -> 3 | F4: =SUMIFS(data!$C:$C,data!$A:$A,"="&xyz!$A4,data!$B:$B,"="&xyz!F$2) -> 7 | G4: =SUMIFS(data!$C:$C,data!$A:$A,"="&xyz!$A4,data!$B:$B,"="&xyz!G$2) -> 6 | H4: =SUMIFS(data!$C:$C,data!$A:$A,"="&xyz!$A4,data!$B:$B,"="&xyz!H$2) -> 6 | I4: =SUMIFS(data!$C:$C,data!$A:$A,"="&xyz!$A4,data!$B:$B,"="&xyz!I$2) -> 7 | J4: =SUMIFS(data!$C:$C,data!$A:$A,"="&xyz!$A4,data!$B:$B,"="&xyz!J$2) -> 5 | ... AP4: =SUMIFS(data!$C:$C,data!$A:$A,"="&xyz!$A4,data!$B:$B,"="&xyz!AP$2) -> 2 | AQ4: =_xlfn.STDEV.S(C4:AP4)/AVERAGE(C4:AP4) -> 0.63202543
A5: ЦИТРАМОН П №20 ТАБ, /ФАРМСТАНДАРТ/ | B5: =AVEDEV(C5:AP5)/AVERAGE(C5:AP5) -> 0.52196532 | C5: =SUMIFS(data!$C:$C,data!$A:$A,"="&xyz!$A5,data!$B:$B,"="&xyz!C$2) -> 7 | D5: =SUMIFS(data!$C:$C,data!$A:$A,"="&xyz!$A5,data!$B:$B,"="&xyz!D$2) -> 7 | E5: =SUMIFS(data!$C:$C,data!$A:$A,"="&xyz!$A5,data!$B:$B,"="&xyz!E$2) -> 6 | F5: =SUMIFS(data!$C:$C,data!$A:$A,"="&xyz!$A5,data!$B:$B,"="&xyz!F$2) -> 5 | G5: =SUMIFS(data!$C:$C,data!$A:$A,"="&xyz!$A5,data!$B:$B,"="&xyz!G$2) -> 4 | H5: =SUMIFS(data!$C:$C,data!$A:$A,"="&xyz!$A5,data!$B:$B,"="&xyz!H$2) -> 5 | I5: =SUMIFS(data!$C:$C,data!$A:$A,"="&xyz!$A5,data!$B:$B,"="&xyz!I$2) -> 3 | J5: =SUMIFS(data!$C:$C,data!$A:$A,"="&xyz!$A5,data!$B:$B,"="&xyz!J$2) -> 3 | ... AP5: =SUMIFS(data!$C:$C,data!$A:$A,"="&xyz!$A5,data!$B:$B,"="&xyz!AP$2) -> 1 | AQ5: =_xlfn.STDEV.S(C5:AP5)/AVERAGE(C5:AP5) -> 0.61817081
A6: ВАЛЕРИАНА ЭКСТРАКТ 20МГ, №50 ТАБ, П/О /БОРИСОВСКИЙ/ | B6: =AVEDEV(C6:AP6)/AVERAGE(C6:AP6) -> 0.48051948 | C6: =SUMIFS(data!$C:$C,data!$A:$A,"="&xyz!$A6,data!$B:$B,"="&xyz!C$2) -> 1 | D6: =SUMIFS(data!$C:$C,data!$A:$A,"="&xyz!$A6,data!$B:$B,"="&xyz!D$2) -> 4 | E6: =SUMIFS(data!$C:$C,data!$A:$A,"="&xyz!$A6,data!$B:$B,"="&xyz!E$2) -> 4 | F6: =SUMIFS(data!$C:$C,data!$A:$A,"="&xyz!$A6,data!$B:$B,"="&xyz!F$2) -> 1 | G6: =SUMIFS(data!$C:$C,data!$A:$A,"="&xyz!$A6,data!$B:$B,"="&xyz!G$2) -> 4 | H6: =SUMIFS(data!$C:$C,data!$A:$A,"="&xyz!$A6,data!$B:$B,"="&xyz!H$2) -> 6 | I6: =SUMIFS(data!$C:$C,data!$A:$A,"="&xyz!$A6,data!$B:$B,"="&xyz!I$2) -> 6 | J6: =SUMIFS(data!$C:$C,data!$A:$A,"="&xyz!$A6,data!$B:$B,"="&xyz!J$2) -> 0 | ... AP6: =SUMIFS(data!$C:$C,data!$A:$A,"="&xyz!$A6,data!$B:$B,"="&xyz!AP$2) -> 3 | AQ6: =_xlfn.STDEV.S(C6:AP6)/AVERAGE(C6:AP6) -> 0.61844536
A7: СФМ ШПРИЦ 2МЛ, 3-Х КОМП, 0,63Х32ММ 23G №10 [SFM] | B7: =AVEDEV(C7:AP7)/AVERAGE(C7:AP7) -> 0.54795134 | C7: =SUMIFS(data!$C:$C,data!$A:$A,"="&xyz!$A7,data!$B:$B,"="&xyz!C$2) -> 1 | D7: =SUMIFS(data!$C:$C,data!$A:$A,"="&xyz!$A7,data!$B:$B,"="&xyz!D$2) -> 2 | E7: =SUMIFS(data!$C:$C,data!$A:$A,"="&xyz!$A7,data!$B:$B,"="&xyz!E$2) -> 0 | F7: =SUMIFS(data!$C:$C,data!$A:$A,"="&xyz!$A7,data!$B:$B,"="&xyz!F$2) -> 1 | G7: =SUMIFS(data!$C:$C,data!$A:$A,"="&xyz!$A7,data!$B:$B,"="&xyz!G$2) -> 1 | H7: =SUMIFS(data!$C:$C,data!$A:$A,"="&xyz!$A7,data!$B:$B,"="&xyz!H$2) -> 3 | I7: =SUMIFS(data!$C:$C,data!$A:$A,"="&xyz!$A7,data!$B:$B,"="&xyz!I$2) -> 2 | J7: =SUMIFS(data!$C:$C,data!$A:$A,"="&xyz!$A7,data!$B:$B,"="&xyz!J$2) -> 0 | ... AP7: =SUMIFS(data!$C:$C,data!$A:$A,"="&xyz!$A7,data!$B:$B,"="&xyz!AP$2) -> 1.5 | AQ7: =_xlfn.STDEV.S(C7:AP7)/AVERAGE(C7:AP7) -> 0.7195565
A8: СФМ ШПРИЦ 5МЛ, 3-Х КОМП, 0,7Х40ММ 22G №10 [SFM] | B8: =AVEDEV(C8:AP8)/AVERAGE(C8:AP8) -> 0.44602076 | C8: =SUMIFS(data!$C:$C,data!$A:$A,"="&xyz!$A8,data!$B:$B,"="&xyz!C$2) -> 2.1 | D8: =SUMIFS(data!$C:$C,data!$A:$A,"="&xyz!$A8,data!$B:$B,"="&xyz!D$2) -> 2.3 | E8: =SUMIFS(data!$C:$C,data!$A:$A,"="&xyz!$A8,data!$B:$B,"="&xyz!E$2) -> 5.2 | F8: =SUMIFS(data!$C:$C,data!$A:$A,"="&xyz!$A8,data!$B:$B,"="&xyz!F$2) -> 5.3 | G8: =SUMIFS(data!$C:$C,data!$A:$A,"="&xyz!$A8,data!$B:$B,"="&xyz!G$2) -> 3 | H8: =SUMIFS(data!$C:$C,data!$A:$A,"="&xyz!$A8,data!$B:$B,"="&xyz!H$2) -> 1 | I8: =SUMIFS(data!$C:$C,data!$A:$A,"="&xyz!$A8,data!$B:$B,"="&xyz!I$2) -> 4.2 | J8: =SUMIFS(data!$C:$C,data!$A:$A,"="&xyz!$A8,data!$B:$B,"="&xyz!J$2) -> 1.1 | ... AP8: =SUMIFS(data!$C:$C,data!$A:$A,"="&xyz!$A8,data!$B:$B,"="&xyz!AP$2) -> 1.6 | AQ8: =_xlfn.STDEV.S(C8:AP8)/AVERAGE(C8:AP8) -> 0.52749727
A9: КЕТОРОЛ ЭКСПРЕСС 10МГ, №20 ТАБ, ДИСПЕРГ, /Д-Р РЕДДИС/ | B9: =AVEDEV(C9:AP9)/AVERAGE(C9:AP9) -> 0.51391753 | C9: =SUMIFS(data!$C:$C,data!$A:$A,"="&xyz!$A9,data!$B:$B,"="&xyz!C$2) -> 3 | D9: =SUMIFS(data!$C:$C,data!$A:$A,"="&xyz!$A9,data!$B:$B,"="&xyz!D$2) -> 1 | E9: =SUMIFS(data!$C:$C,data!$A:$A,"="&xyz!$A9,data!$B:$B,"="&xyz!E$2) -> 1 | F9: =SUMIFS(data!$C:$C,data!$A:$A,"="&xyz!$A9,data!$B:$B,"="&xyz!F$2) -> 12 | G9: =SUMIFS(data!$C:$C,data!$A:$A,"="&xyz!$A9,data!$B:$B,"="&xyz!G$2) -> 8 | H9: =SUMIFS(data!$C:$C,data!$A:$A,"="&xyz!$A9,data!$B:$B,"="&xyz!H$2) -> 5 | I9: =SUMIFS(data!$C:$C,data!$A:$A,"="&xyz!$A9,data!$B:$B,"="&xyz!I$2) -> 5 | J9: =SUMIFS(data!$C:$C,data!$A:$A,"="&xyz!$A9,data!$B:$B,"="&xyz!J$2) -> 4 | ... AP9: =SUMIFS(data!$C:$C,data!$A:$A,"="&xyz!$A9,data!$B:$B,"="&xyz!AP$2) -> 2 | AQ9: =_xlfn.STDEV.S(C9:AP9)/AVERAGE(C9:AP9) -> 0.6886848
A10: РОМАШКИ ЦВЕТКИ 1,5Г, №20 ПАК, /КРАСНОГОРСК/ | B10: =AVEDEV(C10:AP10)/AVERAGE(C10:AP10) -> 0.44577465 | C10: =SUMIFS(data!$C:$C,data!$A:$A,"="&xyz!$A10,data!$B:$B,"="&xyz!C$2) -> 7 | D10: =SUMIFS(data!$C:$C,data!$A:$A,"="&xyz!$A10,data!$B:$B,"="&xyz!D$2) -> 4 | E10: =SUMIFS(data!$C:$C,data!$A:$A,"="&xyz!$A10,data!$B:$B,"="&xyz!E$2) -> 3 | F10: =SUMIFS(data!$C:$C,data!$A:$A,"="&xyz!$A10,data!$B:$B,"="&xyz!F$2) -> 5 | G10: =SUMIFS(data!$C:$C,data!$A:$A,"="&xyz!$A10,data!$B:$B,"="&xyz!G$2) -> 5 | H10: =SUMIFS(data!$C:$C,data!$A:$A,"="&xyz!$A10,data!$B:$B,"="&xyz!H$2) -> 4 | I10: =SUMIFS(data!$C:$C,data!$A:$A,"="&xyz!$A10,data!$B:$B,"="&xyz!I$2) -> 3 | J10: =SUMIFS(data!$C:$C,data!$A:$A,"="&xyz!$A10,data!$B:$B,"="&xyz!J$2) -> 3 | ... AP10: =SUMIFS(data!$C:$C,data!$A:$A,"="&xyz!$A10,data!$B:$B,"="&xyz!AP$2) -> 1 | AQ10: =_xlfn.STDEV.S(C10:AP10)/AVERAGE(C10:AP10) -> 0.61168835
A11: ЛЕВОМЕКОЛЬ 40МГ/Г,+7,5МГ/Г, 40Г, №1 МАЗЬ Д/НАРУЖ,ПРИМ, ТУБА /НИЖФАРМ/ | B11: =AVEDEV(C11:AP11)/AVERAGE(C11:AP11) -> 0.52542373 | C11: =SUMIFS(data!$C:$C,data!$A:$A,"="&xyz!$A11,data!$B:$B,"="&xyz!C$2) -> 2 | D11: =SUMIFS(data!$C:$C,data!$A:$A,"="&xyz!$A11,data!$B:$B,"="&xyz!D$2) -> 5 | E11: =SUMIFS(data!$C:$C,data!$A:$A,"="&xyz!$A11,data!$B:$B,"="&xyz!E$2) -> 2 | F11: =SUMIFS(data!$C:$C,data!$A:$A,"="&xyz!$A11,data!$B:$B,"="&xyz!F$2) -> 3 | G11: =SUMIFS(data!$C:$C,data!$A:$A,"="&xyz!$A11,data!$B:$B,"="&xyz!G$2) -> 4 | H11: =SUMIFS(data!$C:$C,data!$A:$A,"="&xyz!$A11,data!$B:$B,"="&xyz!H$2) -> 2 | I11: =SUMIFS(data!$C:$C,data!$A:$A,"="&xyz!$A11,data!$B:$B,"="&xyz!I$2) -> 7 | J11: =SUMIFS(data!$C:$C,data!$A:$A,"="&xyz!$A11,data!$B:$B,"="&xyz!J$2) -> 2 | ... AP11: =SUMIFS(data!$C:$C,data!$A:$A,"="&xyz!$A11,data!$B:$B,"="&xyz!AP$2) -> 2 | AQ11: =_xlfn.STDEV.S(C11:AP11)/AVERAGE(C11:AP11) -> 0.69066764
A12: ИНГАЛИПТ 30МЛ, АЭРОЗОЛЬ Д/МЕСТ,ПРИМ, БАЛЛОН /ФАРМСТАНДАРТ-ЛЕКСРЕДСТВА/ | B12: =AVEDEV(C12:AP12)/AVERAGE(C12:AP12) -> 0.62222222 | C12: =SUMIFS(data!$C:$C,data!$A:$A,"="&xyz!$A12,data!$B:$B,"="&xyz!C$2) -> 2 | D12: =SUMIFS(data!$C:$C,data!$A:$A,"="&xyz!$A12,data!$B:$B,"="&xyz!D$2) -> 2 | E12: =SUMIFS(data!$C:$C,data!$A:$A,"="&xyz!$A12,data!$B:$B,"="&xyz!E$2) -> 1 | F12: =SUMIFS(data!$C:$C,data!$A:$A,"="&xyz!$A12,data!$B:$B,"="&xyz!F$2) -> 2 | G12: =SUMIFS(data!$C:$C,data!$A:$A,"="&xyz!$A12,data!$B:$B,"="&xyz!G$2) -> 1 | H12: =SUMIFS(data!$C:$C,data!$A:$A,"="&xyz!$A12,data!$B:$B,"="&xyz!H$2) -> 4 | I12: =SUMIFS(data!$C:$C,data!$A:$A,"="&xyz!$A12,data!$B:$B,"="&xyz!I$2) -> 2 | J12: =SUMIFS(data!$C:$C,data!$A:$A,"="&xyz!$A12,data!$B:$B,"="&xyz!J$2) -> 2 | ... AP12: =SUMIFS(data!$C:$C,data!$A:$A,"="&xyz!$A12,data!$B:$B,"="&xyz!AP$2) -> 0 | AQ12: =_xlfn.STDEV.S(C12:AP12)/AVERAGE(C12:AP12) -> 0.746417
A13: СПАЗМАЛГОН №20 ТАБ, | B13: =AVEDEV(C13:AP13)/AVERAGE(C13:AP13) -> 0.5345679 | C13: =SUMIFS(data!$C:$C,data!$A:$A,"="&xyz!$A13,data!$B:$B,"="&xyz!C$2) -> 5 | D13: =SUMIFS(data!$C:$C,data!$A:$A,"="&xyz!$A13,data!$B:$B,"="&xyz!D$2) -> 1 | E13: =SUMIFS(data!$C:$C,data!$A:$A,"="&xyz!$A13,data!$B:$B,"="&xyz!E$2) -> 2 | F13: =SUMIFS(data!$C:$C,data!$A:$A,"="&xyz!$A13,data!$B:$B,"="&xyz!F$2) -> 1 | G13: =SUMIFS(data!$C:$C,data!$A:$A,"="&xyz!$A13,data!$B:$B,"="&xyz!G$2) -> 2 | H13: =SUMIFS(data!$C:$C,data!$A:$A,"="&xyz!$A13,data!$B:$B,"="&xyz!H$2) -> 2 | I13: =SUMIFS(data!$C:$C,data!$A:$A,"="&xyz!$A13,data!$B:$B,"="&xyz!I$2) -> 1 | J13: =SUMIFS(data!$C:$C,data!$A:$A,"="&xyz!$A13,data!$B:$B,"="&xyz!J$2) -> 2 | ... AP13: =SUMIFS(data!$C:$C,data!$A:$A,"="&xyz!$A13,data!$B:$B,"="&xyz!AP$2) -> 3 | AQ13: =_xlfn.STDEV.S(C13:AP13)/AVERAGE(C13:AP13) -> 0.6937732
A14: ИБУКЛИН 400МГ,+325МГ, №10 ТАБ, П/П/О | B14: =AVEDEV(C14:AP14)/AVERAGE(C14:AP14) -> 0.75217391 | C14: =SUMIFS(data!$C:$C,data!$A:$A,"="&xyz!$A14,data!$B:$B,"="&xyz!C$2) -> 0 | D14: =SUMIFS(data!$C:$C,data!$A:$A,"="&xyz!$A14,data!$B:$B,"="&xyz!D$2) -> 1 | E14: =SUMIFS(data!$C:$C,data!$A:$A,"="&xyz!$A14,data!$B:$B,"="&xyz!E$2) -> 2 | F14: =SUMIFS(data!$C:$C,data!$A:$A,"="&xyz!$A14,data!$B:$B,"="&xyz!F$2) -> 0 | G14: =SUMIFS(data!$C:$C,data!$A:$A,"="&xyz!$A14,data!$B:$B,"="&xyz!G$2) -> 0 | H14: =SUMIFS(data!$C:$C,data!$A:$A,"="&xyz!$A14,data!$B:$B,"="&xyz!H$2) -> 3 | I14: =SUMIFS(data!$C:$C,data!$A:$A,"="&xyz!$A14,data!$B:$B,"="&xyz!I$2) -> 3 | J14: =SUMIFS(data!$C:$C,data!$A:$A,"="&xyz!$A14,data!$B:$B,"="&xyz!J$2) -> 0 | ... AP14: =SUMIFS(data!$C:$C,data!$A:$A,"="&xyz!$A14,data!$B:$B,"="&xyz!AP$2) -> 1 | AQ14: =_xlfn.STDEV.S(C14:AP14)/AVERAGE(C14:AP14) -> 1.0418874
... A158: ТРИХОПОЛ 250МГ, №20 ТАБ, /ПОЛЬФАРМА/ | B158: =AVEDEV(C158:AP158)/AVERAGE(C158:AP158) -> 0.87619048 | C158: =SUMIFS(data!$C:$C,data!$A:$A,"="&xyz!$A158,data!$B:$B,"="&xyz!C$2) -> 0 | D158: =SUMIFS(data!$C:$C,data!$A:$A,"="&xyz!$A158,data!$B:$B,"="&xyz!D$2) -> 2 | E158: =SUMIFS(data!$C:$C,data!$A:$A,"="&xyz!$A158,data!$B:$B,"="&xyz!E$2) -> 0 | F158: =SUMIFS(data!$C:$C,data!$A:$A,"="&xyz!$A158,data!$B:$B,"="&xyz!F$2) -> 2 | G158: =SUMIFS(data!$C:$C,data!$A:$A,"="&xyz!$A158,data!$B:$B,"="&xyz!G$2) -> 0 | H158: =SUMIFS(data!$C:$C,data!$A:$A,"="&xyz!$A158,data!$B:$B,"="&xyz!H$2) -> 0 | I158: =SUMIFS(data!$C:$C,data!$A:$A,"="&xyz!$A158,data!$B:$B,"="&xyz!I$2) -> 1 | J158: =SUMIFS(data!$C:$C,data!$A:$A,"="&xyz!$A158,data!$B:$B,"="&xyz!J$2) -> 1 | ... AP158: =SUMIFS(data!$C:$C,data!$A:$A,"="&xyz!$A158,data!$B:$B,"="&xyz!AP$2) -> 2 | AQ158: =_xlfn.STDEV.S(C158:AP158)/AVERAGE(C158:AP158) -> 1.1998411

Sheet Лист3
A1: group
A2: ABC
A3: AAA
A4: AAA
A5: AAA
A6: AAA
A7: AAA
A8: AAA
A9: AAA
A10: AAA
A11: AAA
A12: AAA
... A158: CCB
